fuzz_lightyear/__init__.py
fuzz_lightyear/__main__.py
fuzz_lightyear/config.py
fuzz_lightyear/datastore.py
fuzz_lightyear/discovery.py
fuzz_lightyear/exceptions.py
fuzz_lightyear/fuzzer.py
fuzz_lightyear/generator.py
fuzz_lightyear/main.py
fuzz_lightyear/request.py
fuzz_lightyear/response.py
fuzz_lightyear/result.py
fuzz_lightyear/runner.py
fuzz_lightyear/settings.py
fuzz_lightyear/usage.py
fuzz_lightyear/util.py
fuzz_lightyear/version.py
fuzz_lightyear/output/__init__.py
fuzz_lightyear/output/color.py
fuzz_lightyear/output/formatter.py
fuzz_lightyear/output/interface.py
fuzz_lightyear/output/logging.py
fuzz_lightyear/output/util.py
fuzz_lightyear/plugins/__init__.py
fuzz_lightyear/plugins/base.py
fuzz_lightyear/plugins/idor.py
fuzz_lightyear/supplements/__init__.py
fuzz_lightyear/supplements/abstraction.py
fuzz_lightyear/supplements/auth.py
fuzz_lightyear/supplements/exclude.py
fuzz_lightyear/supplements/factory.py
fuzz_lightyear/supplements/hooks.py
fuzz_lightyear/supplements/include.py
fuzz_lightyear/supplements/request.py
fuzz_lightyear/supplements/setup.py
fuzz_lightyear-0.0.11.dist-info/LICENSE
fuzz_lightyear-0.0.11.dist-info/METADATA
fuzz_lightyear-0.0.11.dist-info/WHEEL
fuzz_lightyear-0.0.11.dist-info/entry_points.txt
fuzz_lightyear-0.0.11.dist-info/top_level.txt
fuzz_lightyear-0.0.11.dist-info/RECORD
