Metadata-Version: 2.1
Name: fuzz_lightyear
Version: 0.0.11
Summary: Vulnerability Discovery through Stateful Swagger Fuzzing
Author: Aaron Loo <aaronloo@yelp.com>, Joey Lee <joeylee@yelp.com>, Victor Zhou <vzhou@yelp.com>
License: Copyright Yelp, Inc. 2019
Keywords: fuzzer,security,swagger
Classifier: Programming Language :: Python :: 3
Classifier: Intended Audience :: Developers
Classifier: Topic :: Security
Classifier: Topic :: Software Development
Classifier: Topic :: Software Development :: Testing :: Acceptance
Classifier: Topic :: Utilities
Classifier: Environment :: Console
Classifier: Operating System :: OS Independent
Classifier: Development Status :: 4 - Beta
License-File: LICENSE
Requires-Dist: bravado
Requires-Dist: cached-property
Requires-Dist: hypothesis >=4.56.1
Requires-Dist: pyyaml
